{
  "id": "treemap-visual",
  "senaryo": "statik",
  "kare": "son",
  "eşikler": {
    "pixelmatch": 0.1,
    "değişenPikselOranı": 0.01,
    "ssim": 0.99
  },
  "geçti": false,
  "değişen_piksel": 10863,
  "değişen_piksel_oranı": 0.040233333333333336,
  "ssim": 0.9019380337585783,
  "ham": {
    "geçti": false,
    "değişen_piksel": 9802,
    "değişen_piksel_oranı": 0.036303703703703706,
    "ssim": 0.8824039424151079
  },
  "tipografi_normalizasyonu": {
    "gaussian_sigma": 0.8,
    "açıklama": "İki görüntüye de aynı Gauss çekirdeği uygulanır; maske ve eşik değişikliği yoktur."
  },
  "yapısal_kontroller": [
    {
      "ad": "treemap_hücre_sınırları_ve_katmanları",
      "geçti": true,
      "açıklama": "Toplam raster oranından bağımsız olarak her hücrenin x/y/width/height sınırı, dolgu, kenarlık, gap, upperLabel ve leafRoot katmanı kilitli ECharts sahnesiyle eşleşmeli",
      "beklenen_düğüm": 245,
      "gerçek_düğüm": 245,
      "karşılaştırılan_alan": 3675,
      "uyuşmazlıklar": []
    }
  ],
  "dosyalar": {
    "referans": "testler/gorsel/referans/74e9e09a0b5687fdd34319121ac73b3022d1483c/default/treemap-visual.png",
    "gerçek": "testler/gorsel/gerçek/default/treemap-visual.png",
    "fark": "testler/gorsel/fark/default/treemap-visual.png",
    "normalize_fark": "testler/gorsel/fark/default/treemap-visual-tipografi.png",
    "sahne": "testler/gorsel/sahneler/treemap-visual.json",
    "referans_sahne": "testler/gorsel/referans/74e9e09a0b5687fdd34319121ac73b3022d1483c/default/sahneler/treemap-visual.json"
  }
}
